construct_additional_obelisks/__init__.py
construct_additional_obelisks/exceptions.py
construct_additional_obelisks/types.py
construct_additional_obelisks/asynchronous/__init__.py
construct_additional_obelisks/asynchronous/client.py
construct_additional_obelisks/asynchronous/consumer.py
construct_additional_obelisks/asynchronous/consumer_test.py
construct_additional_obelisks/asynchronous/producer.py
construct_additional_obelisks/strategies/__init__.py
construct_additional_obelisks/strategies/retry.py
construct_additional_obelisks/sync/__init__.py
construct_additional_obelisks/sync/consumer.py
construct_additional_obelisks/sync/consumer_test.py
construct_additional_obelisks/sync/producer.py
construct_additional_obelisks-0.3.1.dist-info/METADATA
construct_additional_obelisks-0.3.1.dist-info/WHEEL
construct_additional_obelisks-0.3.1.dist-info/RECORD
