Metadata-Version: 2.4
Name: construct-additional-obelisks
Version: 0.3.1
Summary: The one Obelisk client to rule them all
Project-URL: source, https://gitlab.ilabt.imec.be/predict/construct_additional_obelisks
Author-email: Stef Pletinck <Stef.Pletinck@ugent.be>, Pieter Moens <Pieter.Moens@ugent.be>
Requires-Python: >=3.9
Requires-Dist: httpx>=0.28.1
Requires-Dist: pydantic>=2.10.6
Requires-Dist: pytest-asyncio>=0.25.3
Requires-Dist: pytest>=8.3.5
Requires-Dist: ruff>=0.9.6
